networking_huawei/__init__.py
networking_huawei/_i18n.py
networking_huawei/opts.py
networking_huawei/common/__init__.py
networking_huawei/common/constants.py
networking_huawei/common/exceptions.py
networking_huawei/drivers/__init__.py
networking_huawei/drivers/ac/__init__.py
networking_huawei/drivers/ac/client/__init__.py
networking_huawei/drivers/ac/client/restclient.py
networking_huawei/drivers/ac/client/service.py
networking_huawei/drivers/ac/common/__init__.py
networking_huawei/drivers/ac/common/config.py
networking_huawei/drivers/ac/plugins/__init__.py
networking_huawei/drivers/ac/plugins/l3/__init__.py
networking_huawei/drivers/ac/plugins/l3/driver.py
networking_huawei/drivers/ac/plugins/ml2/__init__.py
networking_huawei/drivers/ac/plugins/ml2/driver.py
networking_huawei/drivers/dummy/__init__.py
networking_huawei/drivers/dummy/common/__init__.py
networking_huawei/drivers/dummy/common/config.py
networking_huawei/tests/__init__.py
networking_huawei/tests/unit/__init__.py
networking_huawei/tests/unit/drivers/__init__.py
networking_huawei/tests/unit/drivers/ac/__init__.py
networking_huawei/tests/unit/drivers/ac/client/__init__.py
networking_huawei/tests/unit/drivers/ac/client/test_restclient.py
networking_huawei/tests/unit/drivers/ac/client/test_service.py
networking_huawei/tests/unit/drivers/ac/plugin/__init__.py
networking_huawei/tests/unit/drivers/ac/plugin/l3/__init__.py
networking_huawei/tests/unit/drivers/ac/plugin/l3/test_driver.py
networking_huawei/tests/unit/drivers/ac/plugin/ml2/__init__.py
networking_huawei/tests/unit/drivers/ac/plugin/ml2/test_driver.py
networking_huawei-1.0.0.dist-info/DESCRIPTION.rst
networking_huawei-1.0.0.dist-info/METADATA
networking_huawei-1.0.0.dist-info/RECORD
networking_huawei-1.0.0.dist-info/WHEEL
networking_huawei-1.0.0.dist-info/dependency_links.txt
networking_huawei-1.0.0.dist-info/entry_points.txt
networking_huawei-1.0.0.dist-info/metadata.json
networking_huawei-1.0.0.dist-info/pbr.json
networking_huawei-1.0.0.dist-info/top_level.txt
