Metadata-Version: 2.0
Name: networking-huawei
Version: 1.0.0
Summary: Huawei driver code for interacting with neutron will be developed as part of this project.
Home-page: http://www.openstack.org/
Author: OpenStack
Author-email: openstack-dev@lists.openstack.org
License: UNKNOWN
Platform: UNKNOWN
Classifier: Environment :: OpenStack
Classifier: Intended Audience :: Information Technology
Classifier: Intended Audience :: System Administrators
Classifier: License :: OSI Approved :: Apache Software License
Classifier: Operating System :: POSIX :: Linux
Classifier: Programming Language :: Python
Classifier: Programming Language :: Python :: 2
Classifier: Programming Language :: Python :: 2.7
Requires-Dist: Babel (>=2.3.4)
Requires-Dist: neutron
Requires-Dist: neutron-lib (>=0.1.0)
Requires-Dist: pbr (>=1.6)
